{
  "id": "denovi-2026-11-26",
  "date": "2026-11-26",
  "sourceUrl": "https://denovi.mk/20261126.html",
  "oldDate": {
    "day": "13",
    "month": "Ноември",
    "label": "13 ноември (по стар стил)"
  },
  "newDate": {
    "day": "26",
    "month": "Ноември"
  },
  "notice": "Четврток. Не се пости.",
  "fasting": {
    "isFastDay": false,
    "label": "Без месо"
  },
  "title": "Свети Јован Златоуст",
  "name": "+)Свети Јован Златоуст, архиепископ Константинополски (407)",
  "description": "Патријарх Цариградски. Роден е во Антиохија, во 354 година, од татко Секунд, војвода, и мајка Антуса. Изучувајќи ја грчката философија, Јован се згнаси од грчкото незнабоштво и ја усвои христијанската вера како единствена и целосна вистина. Крштение прими од Мелетиј, патријархот Антиохиски, а потоа примија Крштение и неговите родители. По смртта на родителите се замонаши и почна строго да се подвизува. Тогаш ја напиша книгата „За свештенството“ и тогаш му се јавија светите апостоли Петар и Јован и му прорекоа голема служба, голема благодат, но и големо страдање. Кога требаше да биде посветен за свештеник, се јави ангел Божји: истовремено и на патријархот Флавијан (после Мелетиј) и на самиот Јован. А кога патријархот го ракополагаше, сите видоа светол бел гулаб над Јовановата глава. Прославен заради мудроста, подвигот, и словото со голема власт, беше избран по желба на царот Аркадиј за патријарх Цариградски. Шест години управуваше со Црквата како патријарх со неспоредлива мудрост и ревност. Испрати незнабожечки мисионери кај Келтите и кај Скитите, ја сотре симонијата во Црквата симнувајќи мнозина епископи-симонисти; ја рашири милосрдната дејност на Црквата; напиша посебен чин на светата Литургија; ги посрами еретиците; ја изобличи царицата Евдоксија; Светото Писмо го протолкува со својот златен ум и јазик, на Црквата ѝ остави многу скапоцени книги со неговите беседи. Народот го прослави, завидливците го замразија, царицата двапати го испрати во прогонство. Во прогонство помина три години и се упокои на Крстовден, 14 септември, 407 година, во местото Коман во Ерменија. Пред смртта, повторно му се јавија апостолите Јован и Петар, а и светиот маченик Василиск (се слави на 22 мај), во чијашто црква ја прими светата Причест. „Слава Му на Бога за сè!“, беа неговите последни зборови и со тие зборови душата на златоустиот патријарх замина во Рајот. Од моштите на свети Јован Златоуст главата почива во манастирот Ватопед на Света Гора, а телото во Цариград.",
  "celebrationReason": "Патријарх Цариградски. Роден е во Антиохија, во 354 година, од татко Секунд, војвода, и мајка Антуса. Изучувајќи ја грчката философија, Јован се згнаси од грчкото незнабоштво и ја усвои христијанската вера како единствена и целосна вистина. Крштение прими од Мелетиј, патријархот Антиохиски, а потоа примија Крштение и неговите родители. По смртта на родителите се замонаши и почна строго да се подвизува. Тогаш ја напиша книгата „За свештенството“ и тогаш му се јавија светите апостоли Петар и Јован и му прорекоа голема служба, голема благодат, но и големо страдање. Кога требаше да биде посветен за свештеник, се јави ангел Божји: истовремено и на патријархот Флавијан (после Мелетиј) и на самиот Јован. А кога патријархот го ракополагаше, сите видоа светол бел гулаб над Јовановата глава. Прославен заради мудроста, подвигот, и словото со голема власт, беше избран по желба на царот Аркадиј за патријарх Цариградски. Шест години управуваше со Црквата како патријарх со неспоредлива мудрост и ревност. Испрати незнабожечки мисионери кај Келтите и кај Скитите, ја сотре симонијата во Црквата симнувајќи мнозина епископи-симонисти; ја рашири милосрдната дејност на Црквата; напиша посебен чин на светата Литургија; ги посрами еретиците; ја изобличи царицата Евдоксија; Светото Писмо го протолкува со својот златен ум и јазик, на Црквата ѝ остави многу скапоцени книги со неговите беседи. Народот го прослави, завидливците го замразија, царицата двапати го испрати во прогонство. Во прогонство помина три години и се упокои на Крстовден, 14 септември, 407 година, во местото Коман во Ерменија. Пред смртта, повторно му се јавија апостолите Јован и Петар, а и светиот маченик Василиск (се слави на 22 мај), во чијашто црква ја прими светата Причест. „Слава Му на Бога за сè!“, беа неговите последни зборови и со тие зборови душата на златоустиот патријарх замина во Рајот. Од моштите на свети Јован Златоуст главата почива во манастирот Ватопед на Света Гора, а телото во Цариград.",
  "thumbnail": "./images/2026-11-26-thumb.jpg",
  "image": "./images/2026-11-26-full.jpg",
  "saints": [
    {
      "name": "+)Свети Јован Златоуст, архиепископ Константинополски (407)",
      "detailUrl": "https://denovi.mk/noemvri/26-110.html",
      "thumbnailUrl": "https://denovi.mk/synaxarion/noemvri/26-110-tn.jpg"
    },
    {
      "name": "• Маченици Антонин, Никифор и Герман и маченичката Манета (околу 308)",
      "detailUrl": "https://denovi.mk/noemvri/26-112.html",
      "thumbnailUrl": ""
    },
    {
      "name": "• Новомаченик Дамаскин Атонски (1681)",
      "detailUrl": "https://denovi.mk/noemvri/26-111.html",
      "thumbnailUrl": ""
    },
    {
      "name": "• Свети Квинтијана, епископ Клермонтска и свети Врисиј, епископ Турски (Франција)",
      "detailUrl": "",
      "thumbnailUrl": ""
    },
    {
      "name": "• Свети Евпрасиј, епископ Клермонтски (Франција)",
      "detailUrl": "",
      "thumbnailUrl": ""
    }
  ],
  "attribution": "Content and images sourced from denovi.mk"
}