{
  "id": "denovi-2026-08-20",
  "date": "2026-08-20",
  "sourceUrl": "https://denovi.mk/20260820.html",
  "oldDate": {
    "day": "7",
    "month": "Август",
    "label": "7 август (по стар стил)"
  },
  "newDate": {
    "day": "20",
    "month": "Август"
  },
  "notice": "Четврток, Успенски пост. Строг пост.",
  "fasting": {
    "isFastDay": true,
    "label": "Без месо"
  },
  "title": "Преподобниот маченик Дометиј",
  "name": "Преподобномаченик Дометиј Персиец и неговите два ученика (363)",
  "description": "Роден е во Персија како незнабожец, во времето на царот Константин. Како момче се запозна со верата Христова, го остави незнабоштвото и се крсти. Толку ја засака вистинската вера, што напушти сè светско и се замонаши во еден манастир кај градот Нисивија. Во братството поживеа некое време, па се оддалечи на безмолвие кај некој архимандрит Нурвел, за кого се вели дека шеесет години не јадел ништо варено. Старецот Нурвел го ракоположи за ѓакон, а кога сакаше да го принуди и во чин на свештеник, Дометиј побегна во некоја пустинска гора и се насели во една пештера. Достигна толкаво совршенство низ постот, молитвата, бдението и богомислието, што исцелуваше болни. Кога во тие предели дојде Јулијан Отстапник, слушна за Дометиј, па испрати луѓе коишто го заѕидаа жив во пештерата заедно со неговите двајца ученици. Така заврши овој Божји светител, во 363 година, и се пресели во Божјото Царство.",
  "celebrationReason": "Роден е во Персија како незнабожец, во времето на царот Константин. Како момче се запозна со верата Христова, го остави незнабоштвото и се крсти. Толку ја засака вистинската вера, што напушти сè светско и се замонаши во еден манастир кај градот Нисивија. Во братството поживеа некое време, па се оддалечи на безмолвие кај некој архимандрит Нурвел, за кого се вели дека шеесет години не јадел ништо варено. Старецот Нурвел го ракоположи за ѓакон, а кога сакаше да го принуди и во чин на свештеник, Дометиј побегна во некоја пустинска гора и се насели во една пештера. Достигна толкаво совршенство низ постот, молитвата, бдението и богомислието, што исцелуваше болни. Кога во тие предели дојде Јулијан Отстапник, слушна за Дометиј, па испрати луѓе коишто го заѕидаа жив во пештерата заедно со неговите двајца ученици. Така заврши овој Божји светител, во 363 година, и се пресели во Божјото Царство.",
  "thumbnail": "./images/2026-08-20-thumb.jpg",
  "image": "./images/2026-08-20-full.jpg",
  "saints": [
    {
      "name": "Преподобномаченик Дометиј Персиец и неговите два ученика (363)",
      "detailUrl": "https://denovi.mk/avgust/20-080.html",
      "thumbnailUrl": "https://denovi.mk/synaxarion/avgust/20-080-tn.jpg"
    },
    {
      "name": "Преподобен Пимен Многоболезнен, Печерски (1110)",
      "detailUrl": "https://denovi.mk/avgust/20-084.html",
      "thumbnailUrl": "https://denovi.mk/synaxarion/avgust/20-084-tn.jpg"
    },
    {
      "name": "Преподобен Антониј Оптински (1865)",
      "detailUrl": "https://denovi.mk/avgust/20-082.html",
      "thumbnailUrl": "https://denovi.mk/synaxarion/avgust/20-082-tn.jpg"
    },
    {
      "name": "• Преподобен Пимен, постник Печерски (XIII-XIV)",
      "detailUrl": "",
      "thumbnailUrl": ""
    },
    {
      "name": "• Преподобен Меркуриј Печерски, епископ Смоленски (1239)",
      "detailUrl": "",
      "thumbnailUrl": ""
    },
    {
      "name": "• Маченици Марин воин и Астериј сенатор (260)",
      "detailUrl": "https://denovi.mk/avgust/20-083.html",
      "thumbnailUrl": ""
    },
    {
      "name": "• Преподобен Ор, пустиник Тиваидски (околу 390)",
      "detailUrl": "https://denovi.mk/avgust/20-081.html",
      "thumbnailUrl": ""
    },
    {
      "name": "• Преподобномаченичка Потамија чудотворница",
      "detailUrl": "",
      "thumbnailUrl": ""
    },
    {
      "name": "• Наоѓање на моштите на свети Митрофан, епископ Воронежски (1832)",
      "detailUrl": "",
      "thumbnailUrl": ""
    },
    {
      "name": "• Свештеномаченик Наркис, патријарх Ерусалимски (213)",
      "detailUrl": "https://denovi.mk/avgust/20-085.html",
      "thumbnailUrl": ""
    },
    {
      "name": "• Преподобен Дометиј, Атонски",
      "detailUrl": "",
      "thumbnailUrl": ""
    },
    {
      "name": "• Свети Теодор Сихлиски (Романија)",
      "detailUrl": "",
      "thumbnailUrl": ""
    },
    {
      "name": "• Свети 10.000 подвижници тивски (Грција)",
      "detailUrl": "",
      "thumbnailUrl": ""
    },
    {
      "name": "• Преподобен Иперехиј, од 'Рај'",
      "detailUrl": "",
      "thumbnailUrl": ""
    },
    {
      "name": "• Преподобен Созон Никомидиски",
      "detailUrl": "",
      "thumbnailUrl": ""
    },
    {
      "name": "• Преподобен Теодосиј Нов, исцелител Пелопонески (Грција)",
      "detailUrl": "",
      "thumbnailUrl": ""
    },
    {
      "name": "• Преподобен Никанор од гората Калистрат (Грција)",
      "detailUrl": "",
      "thumbnailUrl": ""
    }
  ],
  "attribution": "Content and images sourced from denovi.mk"
}