{
  "id": "denovi-2028-02-06",
  "date": "2028-02-06",
  "sourceUrl": "https://denovi.mk/20280206.html",
  "oldDate": {
    "day": "24",
    "month": "Јануари",
    "label": "24 јануари (по стар стил)"
  },
  "newDate": {
    "day": "6",
    "month": "Февруари"
  },
  "notice": "Недела. Не се пости.",
  "fasting": {
    "isFastDay": false,
    "label": "Без месо"
  },
  "title": "Преподобна Ксенија",
  "name": "Преподобна Ксенија Римјанка (V)",
  "description": "Родена е во Рим како ќерка-единица на прочуен сенатор. Привлечена од љубовта Христова не сакаше да стапи во брак како што сакаа нејзините родители, па за да ја избегне мажачката побегна од дома тајно, заедно со своите две робинки, па отиде на островот Коа во местото Милас. Овде основа обител на девици што се подвизуваа во христоуподобувањето. Иако беше жена, имаше машка издржливост во постот, молитвата и бдеењето. Често стоеше на молитва по цела ноќ. Беше облечена посиромашно од сите сестри, а врз лебот што го јадеше често истураше пепел од кадилницата. Во мигот на смртта (455 г.) над манастирот се појави прекрасен знак: венец од ѕвезди со крст во средината, посјаен од сонце. Од нејзините мошти мнозина болни добија исцеление. Нејзините робинки го следеа примерот на својата игуманија и кога умреа беа погребани, според нивната желба, крај нозете на блажената Ксенија.",
  "celebrationReason": "Родена е во Рим како ќерка-единица на прочуен сенатор. Привлечена од љубовта Христова не сакаше да стапи во брак како што сакаа нејзините родители, па за да ја избегне мажачката побегна од дома тајно, заедно со своите две робинки, па отиде на островот Коа во местото Милас. Овде основа обител на девици што се подвизуваа во христоуподобувањето. Иако беше жена, имаше машка издржливост во постот, молитвата и бдеењето. Често стоеше на молитва по цела ноќ. Беше облечена посиромашно од сите сестри, а врз лебот што го јадеше често истураше пепел од кадилницата. Во мигот на смртта (455 г.) над манастирот се појави прекрасен знак: венец од ѕвезди со крст во средината, посјаен од сонце. Од нејзините мошти мнозина болни добија исцеление. Нејзините робинки го следеа примерот на својата игуманија и кога умреа беа погребани, според нивната желба, крај нозете на блажената Ксенија.",
  "thumbnail": "./images/71be3f40e9fbe6ca-full.jpg",
  "image": "./images/71be3f40e9fbe6ca-full.jpg",
  "saints": [
    {
      "name": "Преподобна Ксенија Римјанка (V)",
      "detailUrl": "https://denovi.mk/fevruari/06-020.html",
      "thumbnailUrl": "https://denovi.mk/synaxarion/fevruari/06-020-tn.jpg"
    },
    {
      "name": "Преподобен Дионисиј Олимпски и Платински, и Атонски (XIV)",
      "detailUrl": "https://denovi.mk/fevruari/06-025.html",
      "thumbnailUrl": "https://denovi.mk/synaxarion/fevruari/06-025-tn.jpg"
    },
    {
      "name": "Преподобен Филон, епископ Кипарски (V)",
      "detailUrl": "https://denovi.mk/fevruari/06-024.html",
      "thumbnailUrl": "https://denovi.mk/synaxarion/fevruari/06-024-tn.jpg"
    },
    {
      "name": "Блажена Ксенија Петербуршка (XIX)",
      "detailUrl": "https://denovi.mk/fevruari/06-023.html",
      "thumbnailUrl": "https://denovi.mk/synaxarion/fevruari/06-023-tn.jpg"
    },
    {
      "name": "Свети Неофит, затворник Кипарски (XIII)",
      "detailUrl": "https://denovi.mk/fevruari/06-026.html",
      "thumbnailUrl": "https://denovi.mk/synaxarion/fevruari/06-026-tn.jpg"
    },
    {
      "name": "• Маченици Вавила Сицилиски и неговите ученици Тимотеј и Агапиј (III)",
      "detailUrl": "https://denovi.mk/fevruari/06-021.html",
      "thumbnailUrl": ""
    },
    {
      "name": "• Преподобен Македониј, сириски пустиник (околу 420)",
      "detailUrl": "https://denovi.mk/fevruari/06-022.html",
      "thumbnailUrl": ""
    },
    {
      "name": "• Свети Герасим Великопермски (Уствимски) (1441)",
      "detailUrl": "",
      "thumbnailUrl": ""
    },
    {
      "name": "• Маченик Јован Казански (1529)",
      "detailUrl": "",
      "thumbnailUrl": ""
    },
    {
      "name": "• Пренос на моштите на преподобномаченик Анастасиј Персиски (VII)",
      "detailUrl": "",
      "thumbnailUrl": ""
    },
    {
      "name": "• Свети Фелицијан, епископ Фолињански (Италија)",
      "detailUrl": "",
      "thumbnailUrl": ""
    },
    {
      "name": "• Свети Лупицин од Липидиако (Франција)",
      "detailUrl": "",
      "thumbnailUrl": ""
    }
  ],
  "attribution": "Content and images sourced from denovi.mk"
}