{
  "id": "denovi-2027-04-10",
  "date": "2027-04-10",
  "sourceUrl": "https://denovi.mk/20270410.html",
  "oldDate": {
    "day": "28",
    "month": "Март",
    "label": "28 март (по стар стил)"
  },
  "newDate": {
    "day": "10",
    "month": "Април"
  },
  "notice": "Сабота, Велик Пост. Масло.",
  "fasting": {
    "isFastDay": true,
    "label": "Без месо"
  },
  "title": "Светиот маченик Бојан, кнез Бугарски",
  "name": "Свети кнез страстотерпец Бојан Бугарски (околу 830)",
  "description": "Бојан (Енравот) беше бугарски кнез, и беше паганин. Кога на бугарскиот престол стапи неговиот брат Маломир (Владимир), благоверниот кнез Бојан му се обрати со молба да го ослободи од ропство христијанинот Кинамон (Кинам), кој долго време беше во затвор затоа што одби да учествува во паганското жртвопринесување при кнезот Обрит (Крутогон), претходникот на Маломир. Желбата на Бојан беше исполнета, и тој, откако го виде до крајност изнемоштениот Кинамон, го праша зошто тој толку страдал. Во долгата беседа, Кинамон му ја објасни заблудата на паганството и неопходноста од Христовата вера за спасението. На крајот на беседата, тој му рече на кнезот: „Без Христа Исуса нема светлина за умот, нема живот за душата. Тој е единствен учител на човечкиот род и наш Спасител, којшто ја примири Божјата правда преку својата смрт со виновното човештво. Не сакаш погибел? Тогаш верувај во Господа Исуса“. Кнезот Бојан со радост прими Свето Крштение. Новообратениот благоверен кнез, откако се запозна со христијанското благочестие, проникна со искрена љубов кон молитва, пост и богомислие. Маломир, пак, кога дозна за обраќањето во христијанство на својот брат, побара од него да се откаже од Христовата вера и да се врати во паганството. Бојан му одговори: „Јас се гнасам од паганските идоли и го почитувам Христа, Вистинскиот Бог и никој не може да ме оддели од љубовта кон Христа“. Откако го чу одговорот од својот брат, Маломир го осуди на смртна казна. Пред исполнувањето на пресудата, Бојан пророчки кажа: „Верата заради која сега умирам, ќе се распространи по целата бугарска земја. Залудно се надевате дека ќе ја сопрете со мојата смрт. Ќе бидат подигнати храмови на Вистинскиот Бог и служењето Нему нема никогаш да се прекрати, додека идолите и скверните жртвеници ќе исчезнат“. Со последните зборови му се обрати на својот брат Маломир: „Од својата жестокост ти нема да добиеш никаква полза, наскоро и тебе ќе те постигне смрт“.Светиот маченик Бојан пострада за верата во Христа околу 830 година. Неговото пророштво набргу се исполни: Маломир наскоро умре и, бидејќи немаше деца, на престолот седна неговиот постар брат Персијан (836-852). Синот на кнезот Персијан, светиот рамноапостолен кнез Борис (во светото крштение Михаил, се празнува на 2 мај), го покрсти целиот бугарски народ.",
  "celebrationReason": "Бојан (Енравот) беше бугарски кнез, и беше паганин. Кога на бугарскиот престол стапи неговиот брат Маломир (Владимир), благоверниот кнез Бојан му се обрати со молба да го ослободи од ропство христијанинот Кинамон (Кинам), кој долго време беше во затвор затоа што одби да учествува во паганското жртвопринесување при кнезот Обрит (Крутогон), претходникот на Маломир. Желбата на Бојан беше исполнета, и тој, откако го виде до крајност изнемоштениот Кинамон, го праша зошто тој толку страдал. Во долгата беседа, Кинамон му ја објасни заблудата на паганството и неопходноста од Христовата вера за спасението. На крајот на беседата, тој му рече на кнезот: „Без Христа Исуса нема светлина за умот, нема живот за душата. Тој е единствен учител на човечкиот род и наш Спасител, којшто ја примири Божјата правда преку својата смрт со виновното човештво. Не сакаш погибел? Тогаш верувај во Господа Исуса“. Кнезот Бојан со радост прими Свето Крштение. Новообратениот благоверен кнез, откако се запозна со христијанското благочестие, проникна со искрена љубов кон молитва, пост и богомислие. Маломир, пак, кога дозна за обраќањето во христијанство на својот брат, побара од него да се откаже од Христовата вера и да се врати во паганството. Бојан му одговори: „Јас се гнасам од паганските идоли и го почитувам Христа, Вистинскиот Бог и никој не може да ме оддели од љубовта кон Христа“. Откако го чу одговорот од својот брат, Маломир го осуди на смртна казна. Пред исполнувањето на пресудата, Бојан пророчки кажа: „Верата заради која сега умирам, ќе се распространи по целата бугарска земја. Залудно се надевате дека ќе ја сопрете со мојата смрт. Ќе бидат подигнати храмови на Вистинскиот Бог и служењето Нему нема никогаш да се прекрати, додека идолите и скверните жртвеници ќе исчезнат“. Со последните зборови му се обрати на својот брат Маломир: „Од својата жестокост ти нема да добиеш никаква полза, наскоро и тебе ќе те постигне смрт“.Светиот маченик Бојан пострада за верата во Христа околу 830 година. Неговото пророштво набргу се исполни: Маломир наскоро умре и, бидејќи немаше деца, на престолот седна неговиот постар брат Персијан (836-852). Синот на кнезот Персијан, светиот рамноапостолен кнез Борис (во светото крштение Михаил, се празнува на 2 мај), го покрсти целиот бугарски народ.",
  "thumbnail": "./images/850cb7aa8644edf7-full.jpg",
  "image": "./images/850cb7aa8644edf7-full.jpg",
  "saints": [
    {
      "name": "Свети кнез страстотерпец Бојан Бугарски (околу 830)",
      "detailUrl": "https://denovi.mk/april/10-041.html",
      "thumbnailUrl": "https://denovi.mk/synaxarion/april/10-041-tn.jpg"
    },
    {
      "name": "Преподобномаченик Евстратиј Печерски (1097)",
      "detailUrl": "https://denovi.mk/april/10-040.html",
      "thumbnailUrl": "https://denovi.mk/synaxarion/april/10-040-tn.jpg"
    },
    {
      "name": "• Преподобен Иларион Нов, игумен Пеликитски (околу 754)",
      "detailUrl": "https://denovi.mk/april/10-042.html",
      "thumbnailUrl": ""
    },
    {
      "name": "• Преподобен Стефан чудотворец, исповедник, игумен Триглиски (околу 815)",
      "detailUrl": "",
      "thumbnailUrl": ""
    },
    {
      "name": "• Преподобен Иларион Гдовски (1476)",
      "detailUrl": "",
      "thumbnailUrl": ""
    },
    {
      "name": "• Маченици Јона и Варахисиј и со нив Занифан, Лазар, Маруфан, Нарсин, Илија, Марин, Авив, Сивсифин и Сава (околу 330)",
      "detailUrl": "",
      "thumbnailUrl": ""
    },
    {
      "name": "• Свети Исихиј Богослов, презвитер Ерусалимски (V)",
      "detailUrl": "https://denovi.mk/april/10-043.html",
      "thumbnailUrl": ""
    },
    {
      "name": "• Свети Георгиј, епископ, Парод и Петар презвитери, маченици Бугарски",
      "detailUrl": "",
      "thumbnailUrl": ""
    },
    {
      "name": "• Апостол од 70-те Иродион",
      "detailUrl": "",
      "thumbnailUrl": ""
    }
  ],
  "attribution": "Content and images sourced from denovi.mk"
}